ingest4llm/__init__.py
ingest4llm/_client.py
ingest4llm/_constants.py
ingest4llm/_types.py
ingest4llm/ingestor.py
ingest4llm/utils.py
ingest4llm-0.0.1.dist-info/METADATA
ingest4llm-0.0.1.dist-info/WHEEL
ingest4llm-0.0.1.dist-info/RECORD
